FileEncryptionSDK/__init__.py
FileEncryptionSDK/exception/FEException.py
FileEncryptionSDK/exception/__init__.py
FileEncryptionSDK/manager/FEConfig.py
FileEncryptionSDK/manager/FEServer.py
FileEncryptionSDK/manager/FileEncryption.py
FileEncryptionSDK/manager/__init__.py
FileEncryptionSDK/model/Authorize.py
FileEncryptionSDK/model/ChainData.py
FileEncryptionSDK/model/ChainFile.py
FileEncryptionSDK/model/ChainModel.py
FileEncryptionSDK/model/ChainResult.py
FileEncryptionSDK/model/ChainUploadParam.py
FileEncryptionSDK/model/FileAuthorize.py
FileEncryptionSDK/model/FileInfo.py
FileEncryptionSDK/model/OperationResult.py
FileEncryptionSDK/model/Result.py
FileEncryptionSDK/model/UserAction.py
FileEncryptionSDK/model/__init__.py
FileEncryptionSDK/rechain/Base58.py
FileEncryptionSDK/rechain/Client.py
FileEncryptionSDK/rechain/__init__.py
FileEncryptionSDK/rechain/peer_pb2.py
FileEncryptionSDK/rechain/tool.py
FileEncryptionSDK/util/AesEncryptionUtil.py
FileEncryptionSDK/util/ChainDataUtil.py
FileEncryptionSDK/util/DateUtil.py
FileEncryptionSDK/util/DsRepChainUtil.py
FileEncryptionSDK/util/EncryptionUtil.py
FileEncryptionSDK/util/FileUtil.py
FileEncryptionSDK/util/JsonUtil.py
FileEncryptionSDK/util/StringUtil.py
FileEncryptionSDK/util/SystemUtil.py
FileEncryptionSDK/util/__init__.py
FileEncryptionSDK-1.0.7.dist-info/LICENSE
FileEncryptionSDK-1.0.7.dist-info/METADATA
FileEncryptionSDK-1.0.7.dist-info/WHEEL
FileEncryptionSDK-1.0.7.dist-info/top_level.txt
FileEncryptionSDK-1.0.7.dist-info/RECORD
