Metadata-Version: 2.1
Name: FileEncryptionSDK
Version: 1.0.7
Summary: FileEncryptionSDK package
Home-page: https://github.com/pypa/sampleproject
Author: yangyi
Author-email: 54279855@qq.com
License: UNKNOWN
Platform: UNKNOWN
Classifier: Programming Language :: Python :: 3
Classifier: License :: OSI Approved :: MIT License
Classifier: Operating System :: OS Independent
